epochs/__init__.py
epochs/configparser.py
epochs-0.2.0.dist-info/AUTHORS.rst
epochs-0.2.0.dist-info/LICENSE
epochs-0.2.0.dist-info/METADATA
epochs-0.2.0.dist-info/WHEEL
epochs-0.2.0.dist-info/top_level.txt
epochs-0.2.0.dist-info/RECORD
