Metadata-Version: 2.1
Name: epochs
Version: 0.2.0
Summary: Python package to handle configuration files specifying values changing over time
Home-page: https://github.com/mgalloy/epochs
Author: Michael Galloy
Author-email: mgalloy@gmail.com
License: BSD license
Keywords: epochs
Platform: UNKNOWN
Classifier: Development Status :: 2 - Pre-Alpha
Classifier: Intended Audience :: Developers
Classifier: License :: OSI Approved :: BSD License
Classifier: Natural Language :: English
Classifier: Programming Language :: Python :: 3
Classifier: Programming Language :: Python :: 3.5
Classifier: Programming Language :: Python :: 3.6
Classifier: Programming Language :: Python :: 3.7
